alpha_trainer/__init__.py
alpha_trainer/alpha_classes/AlphaGameResult.py
alpha_trainer/alpha_classes/AlphaMove.py
alpha_trainer/alpha_classes/AlphaPlayer.py
alpha_trainer/alpha_classes/AlphaTrainableGame.py
alpha_trainer/alpha_classes/__init__.py
alpha_trainer/expansion_login/__init__.py
alpha_trainer/expansion_login/model_prediction.py
alpha_trainer/expansion_login/simulate_game.py
alpha_trainer/expansion_login/mcts_search/Node.py
alpha_trainer/expansion_login/mcts_search/__init__.py
alpha_trainer/expansion_login/mcts_search/backpropagate.py
alpha_trainer/expansion_login/mcts_search/expand.py
alpha_trainer/expansion_login/mcts_search/mcts_search.py
alpha_trainer/expansion_login/mcts_search/select_best_child.py
alpha_trainer/expansion_login/mcts_search/select_child.py
alpha_trainer/expansion_login/mcts_search/simulate.py
alpha_trainer-0.1.0.dist-info/LICENSE
alpha_trainer-0.1.0.dist-info/METADATA
alpha_trainer-0.1.0.dist-info/WHEEL
alpha_trainer-0.1.0.dist-info/top_level.txt
alpha_trainer-0.1.0.dist-info/RECORD
