Metadata-Version: 2.1
Name: alpha-trainer
Version: 0.1.0
Summary: Framework designed for training machine learning models for custom games
Home-page: https://github.com/pypa/sampleproject
Author: Tesla2000
Author-email: fratajczak124@gmail.com
Project-URL: Homepage, https://github.com/Tesla2000/AlphaTrainer
Classifier: Programming Language :: Python :: 3
Classifier: License :: OSI Approved :: MIT License
Classifier: Operating System :: OS Independent
Requires-Python: >=3.10
License-File: LICENSE
